hdlcrev.v
`timescale 1 ns / 1 ns

module hdlcrev(rst_n , clkr, datar, flagr, ramd, rama, hwr, interrupt);
	input              rst_n;                // 复位，低有效
	input              clkr;                 // 接收数据时钟
	input              datar;                // 数据
	input              flagr;                // 接收开始信号
	output reg [7:0]   ramd ;                 // 接收缓存数据信号
	output reg [8:0]  rama;                 // 接收缓存地址信号
	output reg         hwr;                  // 接收缓存写信号
	output reg         interrupt;                  // 接收完成中断信号

	parameter  [2:0]   HDLC_TYPE_REC_FLAG = 0,HDLC_TYPE_REC_WAIT = 1,HDLC_TYPE_REC_DATA = 2,HDLC_TYPE_REC_OVER = 3,HDLC_TYPE_REC_CLEAR = 4;
	parameter  ADDR_LENGH_REC1 = 9'd510; parameter ADDR_LENGH_REC2 = 9'd511;
	 

	reg syncflag3,flag1,clear; reg [15:0] wait_buf; reg [6: 0] rec_flag_buf;

	always @(negedge rst_n or negedge clkr )
	begin
		if ( (rst_n == 1'b0))
		begin
			rec_flag_buf <= 7'b0000000; syncflag3 <= 1'b0; wait_buf <= 16'b0000000000000000;
		end
		else
		begin
			if(clear == 1'b1)
			begin
				rec_flag_buf <= 7'b0000000; syncflag3 <= 1'b0; wait_buf <= 16'b0000000000000000;
			end
			else
			begin	
				rec_flag_buf <= {rec_flag_buf[5:0], datar};
				wait_buf <= {wait_buf[14:0], rec_flag_buf[6]};
				if (({rec_flag_buf,datar}== 8'b01111110) && (flag1 == 1'b1))
					syncflag3 <= 1'b1;
				else
					syncflag3 <= 1'b0;
			end		
		end
	end

	reg  [2:0 ]  current_state; reg  [7:0 ]   rec_buf; reg  [2:0 ] count;  reg newbyte_buf,bytes_flag,crcwr_flag;
	reg  [4:0 ]  waitnum; reg  [15:0]  rec_crc_buf; reg  [4:0 ]  wait_count; reg  [4: 0]  rec_buf_judge; reg  [7 :0]  ramd0;

	always @(negedge rst_n or negedge clkr)
	begin
		if ( rst_n == 1'b0 )
		begin
			current_state <= HDLC_TYPE_REC_FLAG; rec_buf <= 8'b00000000; count <= 3'b000; newbyte_buf <= 1'b0; bytes_flag <= 1'b0;   crcwr_flag <= 1'b0;
			flag1 <= 1'b1; waitnum <= 5'b10101; wait_count <= 5'b00000; rec_buf_judge <= 5'b00000 ;ramd0 <= 8'b0000_0000; rec_crc_buf <= 16'b0000_0000_0000_0000;
		end
		else
		begin
			case (current_state)
				HDLC_TYPE_REC_FLAG :
				begin
					if (flagr == 1'b1)
					begin
						bytes_flag <= 1'b0;
						newbyte_buf <= 1'b0;
						if (syncflag3 == 1'b1)
						begin
							flag1 <= 1'b0;
							current_state <= HDLC_TYPE_REC_WAIT;
							wait_count <= 5'b00000;
							waitnum <= 5'b10101;
						end
						else
						begin
							current_state <= current_state; flag1 <= flag1;  waitnum <= waitnum; wait_count <= wait_count;
						end
						rec_buf <= rec_buf; count <= count; crcwr_flag <= crcwr_flag;  rec_buf_judge <= rec_buf_judge; ramd0 <= ramd0; rec_crc_buf <= rec_crc_buf;
					end
					else
					begin
						current_state <= current_state; rec_buf <= rec_buf; count <= count; newbyte_buf <= newbyte_buf; bytes_flag <= bytes_flag; crcwr_flag <= crcwr_flag;
                        flag1 <= flag1;  waitnum <= waitnum; wait_count <= wait_count; rec_buf_judge <= rec_buf_judge; ramd0 <= ramd0; rec_crc_buf <= rec_crc_buf;
					end
				end
				HDLC_TYPE_REC_WAIT :
				begin
					crcwr_flag <= 1'b0;
					if (({rec_flag_buf, datar}) == 8'b01111110)
					begin
						wait_count <= 5'b00000;
						waitnum <= 5'b10110;
						current_state <= current_state;  bytes_flag <= bytes_flag; count <= count; rec_buf_judge <= rec_buf_judge; rec_crc_buf <= rec_crc_buf;
					end
					else if (wait_count == waitnum)
					begin
						wait_count <= 5'b00000;
						current_state <= HDLC_TYPE_REC_DATA;
						count <= 3'b000;
						bytes_flag <= 1'b1;
						rec_buf_judge <= 5'b00000;
						rec_crc_buf <= 16'b1111111111111111;
						waitnum <= waitnum;
					end
					else
					begin
						wait_count <= wait_count + 1'b1;
						current_state <= current_state;  bytes_flag <= bytes_flag; count <= count; rec_buf_judge <= rec_buf_judge; rec_crc_buf <= rec_crc_buf; waitnum <= waitnum;
					end
					rec_buf <= rec_buf; newbyte_buf <= newbyte_buf; flag1 <= flag1; ramd0 <= ramd0;
				end
				HDLC_TYPE_REC_DATA :
				begin
					if (rec_buf_judge[4:0] == 5'b11111)
					begin
						rec_buf_judge <= {rec_buf_judge[3:0], 1'b0};
						newbyte_buf <= 1'b0;
						rec_buf <= rec_buf; count <= count; bytes_flag <= bytes_flag;
                        flag1 <= flag1;  waitnum <= waitnum; wait_count <= wait_count; ramd0 <= ramd0; rec_crc_buf <= rec_crc_buf;
					end
					else
					begin
						rec_buf_judge <= {rec_buf_judge[3:0], wait_buf[15]};
						rec_buf <= {wait_buf[15], rec_buf[7:1]};
						rec_crc_buf <= {rec_crc_buf[14:12], (wait_buf[15] ^ rec_crc_buf[11] ^ rec_crc_buf[15]), rec_crc_buf[10:5], (rec_crc_buf[4] ^ rec_crc_buf[15] ^ wait_buf[15]), rec_crc_buf[3:0], (rec_crc_buf[15] ^ wait_buf[15])};
						count <= count + 1'b1;
						if (count == 3'b111)
						begin
							newbyte_buf <= 1'b1;
							ramd0 <= {wait_buf[15], rec_buf[7:1]};
						end
						else
						begin
							newbyte_buf <= 1'b0; ramd0 <= ramd0;
						end
							bytes_flag <= bytes_flag; flag1 <= flag1;  waitnum <= waitnum; wait_count <= wait_count;
					end
					if (({rec_flag_buf, datar}) == 8'b01111110)
					begin
                        current_state <= HDLC_TYPE_REC_OVER;
                        crcwr_flag <= 1'b1;
					end
					else
					begin
						current_state <= current_state; crcwr_flag <= crcwr_flag;
					end
				end
				HDLC_TYPE_REC_OVER :
				begin
					newbyte_buf <= 1'b0;
					flag1 <= 1'b1;
					crcwr_flag <= 0;
					current_state <= HDLC_TYPE_REC_CLEAR; rec_buf <= rec_buf; count <= count; bytes_flag <= bytes_flag;
                    waitnum <= waitnum; wait_count <= wait_count; rec_buf_judge <= rec_buf_judge; ramd0 <= ramd0; rec_crc_buf <= rec_crc_buf;
                end
			    HDLC_TYPE_REC_CLEAR :
			    begin
					if(clear==1)
					begin
						current_state <= HDLC_TYPE_REC_FLAG;
						bytes_flag <= 1'b0;
					end	
					else
					begin					
						current_state <= current_state; 
						bytes_flag <= bytes_flag; 
					end
					rec_buf <= 8'b00000000; count <= 3'b000; newbyte_buf <= 1'b0; crcwr_flag <= 1'b0;
					flag1 <= 1'b1; waitnum <= 5'b10101; wait_count <= 5'b00000; rec_buf_judge <= 5'b00000 ;ramd0 <= 8'b0000_0000; rec_crc_buf <= 16'b0000_0000_0000_0000;   
                end
				default:
				begin
					current_state <= HDLC_TYPE_REC_FLAG; rec_buf <= 8'b00000000; count <= 3'b000; newbyte_buf <= 1'b0; bytes_flag <= 1'b0;   crcwr_flag <= 1'b0;
					flag1 <= 1'b1; waitnum <= 5'b10101; wait_count <= 5'b00000; rec_buf_judge <= 5'b00000 ;ramd0 <= 8'b0000_0000; rec_crc_buf <= 16'b0000_0000_0000_0000;
				end
			endcase
		end
	end

	reg newbytes_flag1;

	always @(negedge rst_n or negedge clkr)
	begin
		if ( rst_n == 1'b0 )
			newbytes_flag1 <= 1'b0;
		else if(clear == 1'b1)
			newbytes_flag1 <= 1'b0;
		else
			newbytes_flag1 <= newbyte_buf;
	end

	reg   [8:0] bytes;

	always @(negedge rst_n or negedge clkr)
	begin
		if (rst_n == 1'b0)
			bytes <= 12'b000000000000;
		else if(clear == 1'b1)
			bytes <= 12'b000000000000;
		else
		begin
			if(bytes_flag == 1'b0)
				bytes <= 12'b000000000000;
			else if(newbytes_flag1 == 1'b1)
				bytes <= bytes + 1'b1;
			else
				bytes <= bytes;
		end
	end

	reg [7: 0] rec_crc_buf1,rec_crc_buf2;

	always @(negedge rst_n or negedge clkr)
	begin: crc_pd_gen
		if ( rst_n == 1'b0 )
		begin
			rec_crc_buf1 <= 8'b00000000; rec_crc_buf2 <= 8'b00000000;
		end
		else if(clear == 1'b1)
		begin
			rec_crc_buf1 <= 8'b00000000; rec_crc_buf2 <= 8'b00000000;
		end		
		else
		begin
			if (newbyte_buf == 1'b1)
			begin
				rec_crc_buf1 <= rec_crc_buf[15:8];
				rec_crc_buf2 <= rec_crc_buf[7:0];
			end
			else
			begin
			    rec_crc_buf1 <= rec_crc_buf1 ;
			    rec_crc_buf2 <= rec_crc_buf2 ;
			end
		end
	end
	/***********数据接收完后，写入一个数据个数******************/
	reg inr1,inr_neg;
	always @(negedge rst_n or negedge clkr)
	begin
		if (rst_n == 1'b0)
		begin
			inr1 <= 1'b0; inr_neg <= 1'b0;
		end
		else
		begin
			inr1 <= inr; inr_neg <= (~inr) & (inr1);
		end
	end

	reg [5:0] cnt_last_write;
	always @(negedge rst_n or negedge clkr)
	begin
		if (rst_n == 1'b0)
			cnt_last_write <= 6'd0;
		else if(inr_neg==1)
			cnt_last_write <= 6'd1;
		else if( (1 <= cnt_last_write )&& (cnt_last_write <= 6'd50) )
			cnt_last_write <= cnt_last_write +6'd1;
		else
			cnt_last_write <= 6'd0;
	end

	always @(negedge rst_n or negedge clkr)
	begin
		if (rst_n == 1'b0)
			clear <= 0;
		else if( (cnt_last_write == 6'd48) || (cnt_last_write == 6'd49) )
			clear <= 1;
		else
			clear <= 0;
	end

	reg last_wren_first;
	always @(negedge rst_n or negedge clkr)
	begin
		if (rst_n == 1'b0)
			last_wren_first <= 0;
		else if(cnt_last_write == 6'd6)
			last_wren_first <= 1;
		else
			last_wren_first <= 0;
	end
	
	reg last_wren_second;
	always @(negedge rst_n or negedge clkr)
	begin
		if (rst_n == 1'b0)
			last_wren_second <= 0;
		else if(cnt_last_write == 6'd14)
			last_wren_second <= 1;
		else
			last_wren_second <= 0;
	end	

	
	/********************ila2********************/
/* 		ila_4  u_ila_4 (
		.clk    ( clkr                   ), // input wire clk
		.probe0 ( datar                  ), // input wire  probe0
		.probe1 ( syncflag3              ), // input wire  probe1
		.probe2 ( flag1                  ), // input wire   probe2
		.probe3 ( current_state          ), // input wire [02:0]  probe3
		.probe4 ( bytes                  ),  // input wire [8:0]  probe4
		.probe5 ( newbytes_flag1         ),  // input wire [00:0]  probe4
		.probe6 ( rama                   ),  // input wire [8 :0]  probe4
		.probe7 ( ramd                   ),  // input wire [07:0]  probe4
		.probe8 ( count                  ),  // input wire [02:0]  probe4
		.probe9 ( wait_buf               ),  // input wire [15:0]  probe4
		.probe10( hwr                    )   // input wire [00:0]  probe4
	);  */
	reg [7:0] ramd1,ramd2;          
	reg [8:0] rama1,rama2;            
	reg hwr1,hwr2,interrupt1,interrupt2; 
	
	
	always @(negedge rst_n or negedge clkr)
	begin
		if (rst_n == 1'b0)
			interrupt1 <= 1'd0;
		else
			interrupt1 <= last_wren_second;
	end
	
	always @(negedge rst_n or negedge clkr)
	begin
		if (rst_n == 1'b0)
		begin
			rama1 <= 9'd0;
			ramd1 <= 8'd0;
			hwr1  <= 1'b0;
		end
		else if(last_wren_first==1)
		begin
			rama1 <= ADDR_LENGH_REC1;
			ramd1 <= bytes[7:0];  
			hwr1  <= 1'b1;
		end
		else if(last_wren_second==1)
		begin
			rama1 <= ADDR_LENGH_REC2;
			ramd1 <= bytes[8];  
			hwr1  <= 1'b1;
		end		
		else
		begin
			rama1 <= bytes;
			ramd1 <= ramd0;
			hwr1 <=  newbytes_flag1;
		end	
	end
	
	//跨时钟域	
	always @(posedge clkr)
	begin
		interrupt2  <= interrupt1;  interrupt  <= interrupt2;
		rama2       <= rama1     ;  rama       <= rama2     ;
		ramd2       <= ramd1     ;  ramd       <= ramd2     ;
		hwr2        <= hwr1      ;  hwr        <= hwr2      ;
	end
	
	assign inr = crcwr_flag;	
endmodule

hdlcrev_testbench.v
// synopsys translate_off
`timescale 1 ns / 1 ps
// synopsys translate_on

module hdlcrev_testbench(
    );
	reg          clk              ;
	reg          rst_n            ;
    reg          datar            ;
    reg          flagr            ;
	reg  [7 :0]  ramd             ;
	reg  [8:0]  rama             ;
	reg          hwr              ;
	reg          interrupt              ;
	integer      i;

	
	always #8 clk  = ~clk;

    initial begin
		clk       = 1;
		rst_n      = 0;
		datar      = 1;
		flagr      = 0;
		
		#128
		rst_n = 1; 
		#16 flagr =1;
		
		#16 datar =0; #16 datar =1;#16 datar =1; #16 datar =1;#16 datar =1;#16 datar =1; #16 datar =1;#16 datar =0;		
		#16 datar =0; #16 datar =1;#16 datar =1; #16 datar =1;#16 datar =1;#16 datar =1; #16 datar =1;#16 datar =0;
		#16 datar =0; #16 datar =1;#16 datar =1; #16 datar =1;#16 datar =1;#16 datar =1; #16 datar =1;#16 datar =0;
		#16 datar =0; #16 datar =1;#16 datar =1; #16 datar =1;#16 datar =1;#16 datar =1; #16 datar =1;#16 datar =0;
		//flagr =0;
		
		#16 datar =0; #16 datar =1;#16 datar =0; #16 datar =1;#16 datar =0;#16 datar =1; #16 datar =0;#16 datar =0;
		#16 datar =1; #16 datar =1;#16 datar =0; #16 datar =1;#16 datar =1;#16 datar =1; #16 datar =0;#16 datar =1;
		#16 datar =1; #16 datar =1;#16 datar =0; #16 datar =0;#16 datar =1;#16 datar =1; #16 datar =0;#16 datar =0;
		#16 datar =1; #16 datar =1;#16 datar =0; #16 datar =1;#16 datar =1;#16 datar =1; #16 datar =0;#16 datar =1;
		#16 datar =1; #16 datar =1;#16 datar =0; #16 datar =0;#16 datar =1;#16 datar =1; #16 datar =0;#16 datar =0;
		#16 datar =0; #16 datar =1;#16 datar =0; #16 datar =1;#16 datar =0;#16 datar =1; #16 datar =0;#16 datar =0;
		#16 datar =1; #16 datar =1;#16 datar =0; #16 datar =1;#16 datar =1;#16 datar =1; #16 datar =0;#16 datar =1;
		#16 datar =1; #16 datar =1;#16 datar =0; #16 datar =0;#16 datar =1;#16 datar =1; #16 datar =0;#16 datar =0;
		#16 datar =1; #16 datar =1;#16 datar =0; #16 datar =1;#16 datar =1;#16 datar =1; #16 datar =0;#16 datar =1;
		#16 datar =1; #16 datar =1;#16 datar =0; #16 datar =0;#16 datar =1;#16 datar =1; #16 datar =0;#16 datar =0;
		
		#16 datar =0; #16 datar =1;#16 datar =1; #16 datar =1;#16 datar =1;#16 datar =1; #16 datar =1;#16 datar =0;		
		#16 datar =0; #16 datar =1;#16 datar =1; #16 datar =1;#16 datar =1;#16 datar =1; #16 datar =1;#16 datar =0;
		#16 datar =0; #16 datar =1;#16 datar =1; #16 datar =1;#16 datar =1;#16 datar =1; #16 datar =1;#16 datar =0;
		#16 datar =0; #16 datar =1;#16 datar =1; #16 datar =1;#16 datar =1;#16 datar =1; #16 datar =1;#16 datar =0;		
		
		/*******************************第二次接收*********************/
		#16000 flagr =1;
		
		#16 datar =0; #16 datar =1;#16 datar =1; #16 datar =1;#16 datar =1;#16 datar =1; #16 datar =1;#16 datar =0;		
		#16 datar =0; #16 datar =1;#16 datar =1; #16 datar =1;#16 datar =1;#16 datar =1; #16 datar =1;#16 datar =0;
		#16 datar =0; #16 datar =1;#16 datar =1; #16 datar =1;#16 datar =1;#16 datar =1; #16 datar =1;#16 datar =0;
		#16 datar =0; #16 datar =1;#16 datar =1; #16 datar =1;#16 datar =1;#16 datar =1; #16 datar =1;#16 datar =0;
		//flagr =0;
		for (i=0;i<100;i=i+1)
		begin
			#16 datar =0; #16 datar =1;#16 datar =0; #16 datar =1;#16 datar =0;#16 datar =1; #16 datar =0;#16 datar =0;
			#16 datar =1; #16 datar =1;#16 datar =0; #16 datar =1;#16 datar =1;#16 datar =1; #16 datar =0;#16 datar =1;
			#16 datar =1; #16 datar =1;#16 datar =0; #16 datar =0;#16 datar =1;#16 datar =1; #16 datar =0;#16 datar =0;
			#16 datar =1; #16 datar =1;#16 datar =0; #16 datar =1;#16 datar =1;#16 datar =1; #16 datar =0;#16 datar =1;
			#16 datar =1; #16 datar =1;#16 datar =0; #16 datar =0;#16 datar =1;#16 datar =1; #16 datar =0;#16 datar =0;
		end

		
		#16 datar =0; #16 datar =1;#16 datar =1; #16 datar =1;#16 datar =1;#16 datar =1; #16 datar =1;#16 datar =0;		
		#16 datar =0; #16 datar =1;#16 datar =1; #16 datar =1;#16 datar =1;#16 datar =1; #16 datar =1;#16 datar =0;
		#16 datar =0; #16 datar =1;#16 datar =1; #16 datar =1;#16 datar =1;#16 datar =1; #16 datar =1;#16 datar =0;
		#16 datar =0; #16 datar =1;#16 datar =1; #16 datar =1;#16 datar =1;#16 datar =1; #16 datar =1;#16 datar =0;		
		
		#128000
		$finish;
	end
	
	initial
    begin
        $dumpfile("hdlcrev_testbench.vcd");
        $dumpvars(0,hdlcrev_testbench);
        $display("hdlcrev_testbench!");
    end

	hdlcrev u_hdlcrev(
		 . rst_n             ( rst_n             ),      //         复位，低有效                          
		 . clkr              ( clk               ),      //         串口时钟                       
		 . datar             ( datar             ),      //         数据                           
		 . flagr             ( flagr             ),      //         接收触发信号  
		           
		 . ramd              ( ramd              ),      // [7:0]   接收缓存数据信号       
		 . rama              ( rama              ),      // [8:0]  接收缓存地址信号       
	     . hwr               ( hwr               ),      //         接收缓存写信号                
		 . interrupt         ( interrupt               )       //         接收完成中断信号              
              
	);	 
	
endmodule

bat/hdlcrev_testbench.vcd
$date
	Tue Dec 18 14:42:49 2018
$end
$version
	Icarus Verilog
$end
$timescale
	1ps
$end
$scope module hdlcrev_testbench $end
$var wire 8 ! ramd [7:0] $end
$var wire 9 " rama [8:0] $end
$var wire 1 # interrupt $end
$var wire 1 $ hwr $end
$var reg 1 % clk $end
$var reg 1 & datar $end
$var reg 1 ' flagr $end
$var reg 1 ( rst_n $end
$var integer 32 ) i [31:0] $end
$scope module u_hdlcrev $end
$var wire 1 % clkr $end
$var wire 1 & datar $end
$var wire 1 ' flagr $end
$var wire 1 * inr $end
$var wire 1 ( rst_n $end
$var reg 9 + bytes [8:0] $end
$var reg 1 , bytes_flag $end
$var reg 1 - clear $end
$var reg 6 . cnt_last_write [5:0] $end
$var reg 3 / count [2:0] $end
$var reg 1 0 crcwr_flag $end
$var reg 3 1 current_state [2:0] $end
$var reg 1 2 flag1 $end
$var reg 1 $ hwr $end
$var reg 1 3 hwr1 $end
$var reg 1 4 hwr2 $end
$var reg 1 5 inr1 $end
$var reg 1 6 inr_neg $end
$var reg 1 # interrupt $end
$var reg 1 7 interrupt1 $end
$var reg 1 8 interrupt2 $end
$var reg 1 9 last_wren_first $end
$var reg 1 : last_wren_second $end
$var reg 1 ; newbyte_buf $end
$var reg 1 < newbytes_flag1 $end
$var reg 9 = rama [8:0] $end
$var reg 9 > rama1 [8:0] $end
$var reg 9 ? rama2 [8:0] $end
$var reg 8 @ ramd [7:0] $end
$var reg 8 A ramd0 [7:0] $end
$var reg 8 B ramd1 [7:0] $end
$var reg 8 C ramd2 [7:0] $end
$var reg 8 D rec_buf [7:0] $end
$var reg 5 E rec_buf_judge [4:0] $end
$var reg 16 F rec_crc_buf [15:0] $end
$var reg 8 G rec_crc_buf1 [7:0] $end
$var reg 8 H rec_crc_buf2 [7:0] $end
$var reg 7 I rec_flag_buf [6:0] $end
$var reg 1 J syncflag3 $end
$var reg 16 K wait_buf [15:0] $end
$var reg 5 L wait_count [4:0] $end
$var reg 5 M waitnum [4:0] $end
$scope begin crc_pd_gen $end
$upscope $end
$upscope $end
$upscope $end
$enddefinitions $end
#0
$dumpvars
b10101 M
b0 L
b0 K
0J
b0 I
b0 H
b0 G
b0 F
b0 E
b0 D
bx C
b0 B
b0 A
bx @
bx ?
b0 >
bx =
0<
0;
0:
09
x8
07
06
05
x4
03
12
b0 1
00
b0 /
b0 .
0-
0,
b0 +
0*
bx )
0(
0'
1&
1%
x$
x#
bx "
bx !
$end
#8000
0%
#16000
04
b0 C
b0 ?
08
1%
#24000
0%
#32000
0$
b0 !
b0 @
b0 "
b0 =
0#
1%
#40000
0%
#48000
1%
#56000
0%
#64000
1%
#72000
0%
#80000
1%
#88000
0%
#96000
1%
#104000
0%
#112000
1%
#120000
0%
#128000
1%
1(
#136000
b1 I
0%
#144000
1%
1'
#152000
b11 I
0%
#160000
1%
0&
#168000
b110 I
0%
#176000
1%
1&
#184000
b1101 I
0%
#192000
1%
#200000
b11011 I
0%
#208000
1%
#216000
b110111 I
0%
#224000
1%
#232000
b1101111 I
0%
#240000
1%
#248000
b1 K
b1011111 I
0%
#256000
1%
#264000
b11 K
b111111 I
0%
#272000
1%
0&
#280000
1J
b110 K
b1111110 I
0%
#288000
1%
#296000
b1 1
02
0J
b1101 K
b1111100 I
0%
#304000
1%
1&
#312000
b11011 K
b1111001 I
b1 L
0%
#320000
1%
#328000
b10 L
b110111 K
b1110011 I
0%
#336000
1%
#344000
b1101111 K
b1100111 I
b11 L
0%
#352000
1%
#360000
b100 L
b11011111 K
b1001111 I
0%
#368000
1%
#376000
b110111111 K
b11111 I
b101 L
0%
#384000
1%
#392000
b110 L
b1101111110 K
b111111 I
0%
#400000
1%
0&
#408000
b11011111100 K
b1111110 I
b10110 M
b0 L
0%
#416000
1%
#424000
b1 L
b110111111001 K
b1111100 I
0%
#432000
1%
1&
#440000
b1101111110011 K
b1111001 I
b10 L
0%
#448000
1%
#456000
b11 L
b11011111100111 K
b1110011 I
0%
#464000
1%
#472000
b110111111001111 K
b1100111 I
b100 L
0%
#480000
1%
#488000
b101 L
b1101111110011111 K
b1001111 I
0%
#496000
1%
#504000
b1011111100111111 K
b11111 I
b110 L
0%
#512000
1%
#520000
b111 L
b111111001111110 K
b111111 I
0%
#528000
1%
0&
#536000
b1111110011111100 K
b1111110 I
b0 L
0%
#544000
1%
#552000
b1 L
b1111100111111001 K
b1111100 I
0%
#560000
1%
1&
#568000
b1111001111110011 K
b1111001 I
b10 L
0%
#576000
1%
#584000
b11 L
b1110011111100111 K
b1110011 I
0%
#592000
1%
#600000
b1100111111001111 K
b1100111 I
b100 L
0%
#608000
1%
#616000
b101 L
b1001111110011111 K
b1001111 I
0%
#624000
1%
#632000
b11111100111111 K
b11111 I
b110 L
0%
#640000
1%
#648000
b111 L
b111111001111110 K
b111111 I
0%
#656000
1%
0&
#664000
b1111110011111100 K
b1111110 I
b0 L
0%
#672000
1%
#680000
b1 L
b1111100111111001 K
b1111100 I
0%
#688000
1%
1&
#696000
b1111001111110011 K
b1111001 I
b10 L
0%
#704000
1%
0&
#712000
b11 L
b1110011111100111 K
b1110010 I
0%
#720000
1%
1&
#728000
b1100111111001111 K
b1100101 I
b100 L
0%
#736000
1%
0&
#744000
b101 L
b1001111110011111 K
b1001010 I
0%
#752000
1%
1&
#760000
b11111100111111 K
b10101 I
b110 L
0%
#768000
1%
0&
#776000
b111 L
b111111001111110 K
b101010 I
0%
#784000
1%
#792000
b1111110011111100 K
b1010100 I
b1000 L
0%
#800000
1%
1&
#808000
b1001 L
b1111100111111001 K
b101001 I
0%
#816000
1%
#824000
b1111001111110010 K
b1010011 I
b1010 L
0%
#832000
1%
0&
#840000
b1011 L
b1110011111100101 K
b100110 I
0%
#848000
1%
1&
#856000
b1100111111001010 K
b1001101 I
b1100 L
0%
#864000
1%
#872000
b1101 L
b1001111110010101 K
b11011 I
0%
#880000
1%
#888000
b11111100101010 K
b110111 I
b1110 L
0%
#896000
1%
0&
#904000
b1111 L
b111111001010100 K
b1101110 I
0%
#912000
1%
1&
#920000
b1111110010101001 K
b1011101 I
b10000 L
0%
#928000
1%
#936000
b10001 L
b1111100101010011 K
b111011 I
0%
#944000
1%
#952000
b1111001010100110 K
b1110111 I
b10010 L
0%
#960000
1%
0&
#968000
b10011 L
b1110010101001101 K
b1101110 I
0%
#976000
1%
#984000
b1100101010011011 K
b1011100 I
b10100 L
0%
#992000
1%
1&
#1000000
b10101 L
b1001010100110111 K
b111001 I
0%
#1008000
1%
#1016000
b10101001101110 K
b1110011 I
b10110 L
0%
#1024000
1%
0&
#1032000
b1111111111111111 F
1,
b10 1
b0 L
b101010011011101 K
b1100110 I
0%
#1040000
1%
#1048000
b1010100110111011 K
b1001100 I
b1 /
b1110111111011111 F
0%
#1056000
1%
1&
#1064000
b10 /
b1101111110111110 F
b10000000 D
b1 E
b101001101110111 K
b11001 I
0%
#1072000
1%
#1080000
b1010011011101110 K
b110011 I
b11 /
b1010111101011101 F
b1000000 D
b10 E
0%
#1088000
1%
0&
#1096000
b100 /
b101111010111010 F
b10100000 D
b101 E
b100110111011100 K
b1100110 I
0%
#1104000
1%
1&
#1112000
b1001101110111001 K
b1001101 I
b101 /
b1011110101110100 F
b1010000 D
b1010 E
0%
#1120000
1%
#1128000
b110 /
b111101011101000 F
b10101000 D
b10101 E
b11011101110011 K
b11011 I
0%
#1136000
1%
#1144000
b110111011100110 K
b110111 I
b111 /
b1111010111010000 F
b1010100 D
b1010 E
0%
#1152000
1%
0&
#1160000
b101010 A
1;
b0 /
b1111101110000001 F
b101010 D
b10100 E
b1101110111001100 K
b1101110 I
0%
#1168000
1%
1&
#1176000
b10000001 H
b11111011 G
b1011101110011001 K
b1011101 I
0;
b1 /
b1111011100000010 F
b10010101 D
b1001 E
1<
b101010 B
0%
#1184000
b101010 C
1%
#1192000
13
b1 +
0<
b10 /
b1110111000000100 F
b11001010 D
b10011 E
b111011100110011 K
b111011 I
0%
#1200000
14
b101010 !
b101010 @
1%
#1208000
b1110111001100110 K
b1110111 I
b11 /
b1100110000101001 F
b1100101 D
b110 E
03
b1 >
0%
#1216000
1$
04
b1 ?
1%
0&
#1224000
b100 /
b1001100001010010 F
b10110010 D
b1101 E
b1101110011001101 K
b1101110 I
0%
#1232000
0$
b1 "
b1 =
1%
#1240000
b1011100110011011 K
b1011100 I
b101 /
b11000010100100 F
b11011001 D
b11011 E
0%
#1248000
1%
1&
#1256000
b110 /
b111000101101001 F
b11101100 D
b10111 E
b111001100110111 K
b111001 I
0%
#1264000
1%
#1272000
b1110011001101110 K
b1110011 I
b111 /
b1110001011010010 F
b1110110 D
b1110 E
0%
#1280000
1%
0&
#1288000
b10111011 A
1;
b0 /
b1100010110100100 F
b10111011 D
b11101 E
b1100110011011101 K
b1100110 I
0%
#1296000
1%
#1304000
b10100100 H
b11000101 G
b1001100110111011 K
b1001100 I
0;
b1 /
b1000101101001000 F
b11011101 D
b11011 E
1<
b10111011 B
0%
#1312000
b10111011 C
1%
#1320000
13
b10 +
0<
b10 /
b1011010010000 F
b11101110 D
b10111 E
b11001101110111 K
b11000 I
0%
#1328000
14
b10111011 !
b10111011 @
1%
1&
#1336000
b110011011101110 K
b110001 I
b11 /
b10110100100000 F
b1110111 D
b1110 E
03
b10 >
0%
#1344000
1$
04
b10 ?
1%
0&
#1352000
b100 /
b101101001000000 F
b111011 D
b11100 E
b1100110111011100 K
b1100010 I
0%
#1360000
0$
b10 "
b10 =
1%
1&
#1368000
b1001101110111001 K
b1000101 I
b101 /
b1010010010100001 F
b10011101 D
b11001 E
0%
#1376000
1%
0&
#1384000
b110 /
b100100101000010 F
b11001110 D
b10011 E
b11011101110011 K
b1010 I
0%
#1392000
1%
1&
#1400000
b110111011100110 K
b10101 I
b111 /
b1001001010000100 F
b1100111 D
b110 E
0%
#1408000
1%
0&
#1416000
b110011 A
1;
b0 /
b11010100101001 F
b110011 D
b1100 E
b1101110111001100 K
b101010 I
0%
#1424000
1%
#1432000
b101001 H
b110101 G
b1011101110011000 K
b1010100 I
0;
b1 /
b111101001110011 F
b10011001 D
b11001 E
1<
b110011 B
0%
#1440000
b110011 C
1%
1&
#1448000
13
b11 +
0<
b10 /
b1110010011000111 F
b11001100 D
b10011 E
b111011100110001 K
b101001 I
0%
#1456000
14
b110011 !
b110011 @
1%
#1464000
b1110111001100010 K
b1010011 I
b11 /
b1101100110101111 F
b1100110 D
b110 E
03
b11 >
0%
#1472000
1$
04
b11 ?
1%
0&
#1480000
b100 /
b1011001101011110 F
b10110011 D
b1101 E
b1101110011000101 K
b100110 I
0%
#1488000
0$
b11 "
b11 =
1%
1&
#1496000
b1011100110001010 K
b1001101 I
b101 /
b110011010111100 F
b11011001 D
b11011 E
0%
#1504000
1%
#1512000
b110 /
b1101110101011001 F
b11101100 D
b10111 E
b111001100010101 K
b11011 I
0%
#1520000
1%
#1528000
b1110011000101010 K
b110111 I
b111 /
b1010101010010011 F
b1110110 D
b1110 E
0%
#1536000
1%
0&
#1544000
b10111011 A
1;
b0 /
b101010100100110 F
b10111011 D
b11101 E
b1100110001010100 K
b1101110 I
0%
#1552000
1%
1&
#1560000
b100110 H
b1010101 G
b1001100010101001 K
b1011101 I
0;
b1 /
b1011101001101101 F
b11011101 D
b11011 E
1<
b10111011 B
0%
#1568000
b10111011 C
1%
#1576000
13
b100 +
0<
b10 /
b111010011011010 F
b11101110 D
b10111 E
b11000101010011 K
b111011 I
0%
#1584000
14
b10111011 !
b10111011 @
1%
#1592000
b110001010100110 K
b1110111 I
b11 /
b1110100110110100 F
b1110111 D
b1110 E
03
b100 >
0%
#1600000
1$
04
b100 ?
1%
0&
#1608000
b100 /
b1100001101001001 F
b111011 D
b11100 E
b1100010101001101 K
b1101110 I
0%
#1616000
0$
b100 "
b100 =
1%
#1624000
b1000101010011011 K
b1011100 I
b101 /
b1000011010010010 F
b10011101 D
b11001 E
0%
#1632000
1%
1&
#1640000
b110 /
b110100100100 F
b11001110 D
b10011 E
b1010100110111 K
b111001 I
0%
#1648000
1%
#1656000
b10101001101110 K
b1110011 I
b111 /
b1101001001000 F
b1100111 D
b110 E
0%
#1664000
1%
0&
#1672000
b110011 A
1;
b0 /
b11010010010000 F
b110011 D
b1100 E
b101010011011101 K
b1100110 I
0%
#1680000
1%
#1688000
b10010000 H
b110100 G
b1010100110111011 K
b1001100 I
0;
b1 /
b110100100100000 F
b11001 D
b11000 E
1<
b110011 B
0%
